JupiterMag/Globals.py
JupiterMag/TraceField.py
JupiterMag/_CFunctions.py
JupiterMag/_CppLib.py
JupiterMag/__init__.py
JupiterMag/_ptr2D.py
JupiterMag/ct.py
JupiterMag/Con2020/Config.py
JupiterMag/Con2020/Field.py
JupiterMag/Con2020/Test.py
JupiterMag/Con2020/_CFunctions.py
JupiterMag/Con2020/_ReadTestData.py
JupiterMag/Con2020/__init__.py
JupiterMag/CoordConv/MagtoSIII.py
JupiterMag/CoordConv/SIIItoMag.py
JupiterMag/CoordConv/__init__.py
JupiterMag/Internal/Config.py
JupiterMag/Internal/Field.py
JupiterMag/Internal/Test.py
JupiterMag/Internal/_CFunctions.py
JupiterMag/Internal/_ReadTestPos.py
JupiterMag/Internal/__init__.py
JupiterMag/Tools/GetLegendHandLab.py
JupiterMag/Tools/JupiterOval.py
JupiterMag/Tools/PlotJupiter.py
JupiterMag/Tools/Python.py
JupiterMag/Tools/TestPigtail.py
JupiterMag/Tools/TestTrace.py
JupiterMag/Tools/Timer.py
JupiterMag/Tools/__init__.py
JupiterMag/__data/testdata.bin
JupiterMag/__data/testpos.dat
JupiterMag/__data/libjupitermag/.DS_Store
JupiterMag/__data/libjupitermag/.git
JupiterMag/__data/libjupitermag/.gitignore
JupiterMag/__data/libjupitermag/.gitmodules
JupiterMag/__data/libjupitermag/CITATION.cff
JupiterMag/__data/libjupitermag/LICENSE
JupiterMag/__data/libjupitermag/README.md
JupiterMag/__data/libjupitermag/VERSION
JupiterMag/__data/libjupitermag/clean.bat
JupiterMag/__data/libjupitermag/compile.bat
JupiterMag/__data/libjupitermag/generateheader.py
JupiterMag/__data/libjupitermag/getlibs.sh
JupiterMag/__data/libjupitermag/makefile
JupiterMag/__data/libjupitermag/__pycache__/generateheader.cpython-38.pyc
JupiterMag/__data/libjupitermag/build/bessel.o
JupiterMag/__data/libjupitermag/build/coeffs.o
JupiterMag/__data/libjupitermag/build/con2020.o
JupiterMag/__data/libjupitermag/build/flux.o
JupiterMag/__data/libjupitermag/build/internal.o
JupiterMag/__data/libjupitermag/build/internalmodel.o
JupiterMag/__data/libjupitermag/build/interptraceclosestpos.o
JupiterMag/__data/libjupitermag/build/libcon2020.o
JupiterMag-1.1.2.dist-info/LICENSE
JupiterMag-1.1.2.dist-info/METADATA
JupiterMag-1.1.2.dist-info/WHEEL
JupiterMag-1.1.2.dist-info/top_level.txt
JupiterMag-1.1.2.dist-info/RECORD
