Metadata-Version: 2.1
Name: JupiterMag
Version: 1.1.2
Summary: Some magnetic field models for Jupiter
Home-page: https://github.com/mattkjames7/JupiterMag
Author: Matthew Knight James
Author-email: mattkjames7@gmail.com
License: UNKNOWN
Platform: UNKNOWN
Classifier: Programming Language :: Python :: 3
Classifier: License :: OSI Approved :: GNU General Public License (GPL)
Classifier: Operating System :: POSIX
License-File: LICENSE
Requires-Dist: DateTimeTools
Requires-Dist: PyFileIO
Requires-Dist: RecarrayTools
Requires-Dist: matplotlib
Requires-Dist: numpy
Requires-Dist: scipy
